lifetime_value/__init__.py
lifetime_value-0.0.6.dist-info/METADATA
lifetime_value-0.0.6.dist-info/WHEEL
lifetime_value-0.0.6.dist-info/top_level.txt
lifetime_value-0.0.6.dist-info/RECORD
