Metadata-Version: 2.1
Name: lifetime-value
Version: 0.0.6
Summary: Lifetime value function over time.
Home-page: https://github.com/merijnvanes/lifetime-value.git
Author: Merijn van Es
Author-email: merijnvanes@gmail.com
License: UNKNOWN
Keywords: lifetime value,ltv,customer lifetime value,clv
Platform: UNKNOWN
Requires-Python: >=3.7
Requires-Dist: pandas (>=1.2.2)
Requires-Dist: numpy (>=1.20.2)
